<?xml version="1.0" encoding="UTF-8"?>
<STEP-ProductInformation ContextID="DE-de" WorkspaceID="Approved" UseContextLocale="false">
    <Qualifiers>
        <Qualifier ID="eng">
            <DimensionPointLink DimensionPointID="eng"></DimensionPointLink>
            <Context ID="EN All All" Priority="1"></Context>
        </Qualifier>
    </Qualifiers>
    <ListsOfValues>
        <ListOfValue ID="PhoneType" ParentID="Vinl_LOV" AllowUserValueAddition="false" UseValueID="true">
            <Name QualifierID="eng">PhoneType</Name>
            <Validation BaseType="text" MinValue="" MaxValue="" MaxLength="100" InputMask=""></Validation>
            <MetaData>
                <ValueGroup AttributeID="AttributeHelpText">
                    <Value Derived="true" DerivedContextID="Context1">&lt;b&gt;ID = &lt;/b&gt;PhoneType
&lt;br/&gt;&lt;b&gt;Name = &lt;/b&gt;
&lt;br/&gt;&lt;b&gt;Description = &lt;/b&gt;N/A
&lt;br/&gt;&lt;b&gt;Help URL = &lt;/b&gt;&lt;a href="N/A"&gt;N/A&lt;/a&gt;
&lt;br/&gt;&lt;b&gt;Wiki = &lt;/b&gt;&lt;a href="</Value>
                    <Value Derived="true" DerivedContextID="DE-de">&lt;b&gt;ID = &lt;/b&gt;PhoneType
&lt;br/&gt;&lt;b&gt;Name = &lt;/b&gt;
&lt;br/&gt;&lt;b&gt;Description = &lt;/b&gt;N/A
&lt;br/&gt;&lt;b&gt;Help URL = &lt;/b&gt;&lt;a href="N/A"&gt;N/A&lt;/a&gt;
&lt;br/&gt;&lt;b&gt;Wiki = &lt;/b&gt;&lt;a href="</Value>
                    <Value Derived="true" DerivedContextID="EN All All">&lt;b&gt;ID = &lt;/b&gt;PhoneType
&lt;br/&gt;&lt;b&gt;Name = &lt;/b&gt;PhoneType
&lt;br/&gt;&lt;b&gt;Description = &lt;/b&gt;N/A
&lt;br/&gt;&lt;b&gt;Help URL = &lt;/b&gt;&lt;a href="N/A"&gt;N/A&lt;/a&gt;
&lt;br/&gt;&lt;b&gt;Wiki = &lt;/b&gt;&lt;a href="</Value>
                    <Value Derived="true" DerivedContextID="FR All All">&lt;b&gt;ID = &lt;/b&gt;PhoneType
&lt;br/&gt;&lt;b&gt;Name = &lt;/b&gt;
&lt;br/&gt;&lt;b&gt;Description = &lt;/b&gt;N/A
&lt;br/&gt;&lt;b&gt;Help URL = &lt;/b&gt;&lt;a href="N/A"&gt;N/A&lt;/a&gt;
&lt;br/&gt;&lt;b&gt;Wiki = &lt;/b&gt;&lt;a href="</Value>
                    <Value Derived="true" DerivedContextID="GL">&lt;b&gt;ID = &lt;/b&gt;PhoneType
&lt;br/&gt;&lt;b&gt;Name = &lt;/b&gt;
&lt;br/&gt;&lt;b&gt;Description = &lt;/b&gt;N/A
&lt;br/&gt;&lt;b&gt;Help URL = &lt;/b&gt;&lt;a href="N/A"&gt;N/A&lt;/a&gt;
&lt;br/&gt;&lt;b&gt;Wiki = &lt;/b&gt;&lt;a href="</Value>
                </ValueGroup>
            </MetaData>
            <ValueGroup ID="1">
                <Value>OFFICE PHONE</Value>
            </ValueGroup>
            <ValueGroup ID="2">
                <Value>OFFICE FAX</Value>
            </ValueGroup>
            <ValueGroup ID="3">
                <Value>OTHER</Value>
            </ValueGroup>
            <ValueGroup ID="4">
                <Value>MOBILE PHONE</Value>
            </ValueGroup>
            <ValueGroup ID="5">
                <Value>HOME PHONE</Value>
            </ValueGroup>
            <ValueGroup ID="6">
                <Value>HOME FAX</Value>
            </ValueGroup>
        </ListOfValue>
    </ListsOfValues>
</STEP-ProductInformation>