<?xml version="1.0" encoding="UTF-8"?>
<STEP-ProductInformation ContextID="DE-de" WorkspaceID="Approved" UseContextLocale="false">
    <UserGroupList>
        <UserGroup ID="ProcurementManagerUsers" ReadOnly="false">
            <Name>Procurement Manager Users</Name>
            <PrivilegeRule ActionSetID="DataContainerApprove" EntityID="100305"></PrivilegeRule>
            <PrivilegeRule ActionSetID="DataContainerCreate" EntityID="100305"></PrivilegeRule>
            <PrivilegeRule ActionSetID="DataContainerModify" EntityID="100305"></PrivilegeRule>
            <PrivilegeRule ActionSetID="DataContainerView" EntityID="100305"></PrivilegeRule>
            <PrivilegeRule ActionSetID="ProcurementManagerApprove" ClassificationID="SupplierClassificationsRoot" UserTypeID="SupplierAssetsClassification"></PrivilegeRule>
            <PrivilegeRule ActionSetID="ProcurementManagerApprove" ClassificationID="SupplierClassificationsRoot" UserTypeID="SupplierClassification"></PrivilegeRule>
            <PrivilegeRule ActionSetID="ProcurementManagerApprove" ClassificationID="SupplierClassificationsRoot" UserTypeID="SupplierClassificationsRoot"></PrivilegeRule>
            <PrivilegeRule ActionSetID="ProcurementManagerApprove" ClassificationID="SupplierClassificationsRoot" UserTypeID="SupplierEntitiesClassification"></PrivilegeRule>
            <PrivilegeRule ActionSetID="ProcurementManagerApprove" ClassificationID="SupplierClassificationsRoot" UserTypeID="SupplierProductsClassification"></PrivilegeRule>
            <PrivilegeRule ActionSetID="ProcurementManagerApprove" STEPWorkflowID="ContactMaintenanceSelfService" STEPWorkflowStateID="Initial" UserTypeID="ContactPerson"></PrivilegeRule>
            <PrivilegeRule ActionSetID="ProcurementManagerApprove" STEPWorkflowID="ContactMaintenanceSelfService" STEPWorkflowStateID="ProcurementEnrichment" UserTypeID="ContactPerson"></PrivilegeRule>
            <PrivilegeRule ActionSetID="ProcurementManagerApprove" STEPWorkflowID="ContactOnboardingSelfService" STEPWorkflowStateID="Initial" UserTypeID="ContactPerson"></PrivilegeRule>
            <PrivilegeRule ActionSetID="ProcurementManagerApprove" STEPWorkflowID="ContactOnboardingSelfService" STEPWorkflowStateID="ProcurementEnrichment" UserTypeID="ContactPerson"></PrivilegeRule>
            <PrivilegeRule ActionSetID="ProcurementManagerCreate" EntityID="100305" UserTypeID="ContactPerson"></PrivilegeRule>
            <PrivilegeRule ActionSetID="ProcurementManagerCreate" EntityID="100305" UserTypeID="Supplier"></PrivilegeRule>
            <PrivilegeRule ActionSetID="ProcurementManagerDelete" ClassificationID="SupplierClassificationsRoot" UserTypeID="SupplierEntitiesClassification"></PrivilegeRule>
            <PrivilegeRule ActionSetID="ProcurementManagerModify" UserTypeID="ContactPerson" ObjectCreation="true" AttributeGroupID="ProcurementModify"></PrivilegeRule>
            <PrivilegeRule ActionSetID="ProcurementManagerModify" UserTypeID="Supplier" ObjectCreation="true" AttributeGroupID="ProcurementModify"></PrivilegeRule>
            <PrivilegeRule ActionSetID="ProcurementManagerModify" STEPWorkflowID="ContactMaintenanceNoSelfService" STEPWorkflowStateID="Initial" UserTypeID="ContactPerson" AttributeGroupID="ProcurementModify"></PrivilegeRule>
            <PrivilegeRule ActionSetID="ProcurementManagerModify" STEPWorkflowID="ContactMaintenanceNoSelfService" STEPWorkflowStateID="SalesProcurementReview" UserTypeID="ContactPerson" AttributeGroupID="ProcurementModify"></PrivilegeRule>
            <PrivilegeRule ActionSetID="ProcurementManagerModify" STEPWorkflowID="ContactMaintenanceSelfService" STEPWorkflowStateID="Initial" UserTypeID="ContactPerson" AttributeGroupID="ProcurementModify"></PrivilegeRule>
            <PrivilegeRule ActionSetID="ProcurementManagerModify" STEPWorkflowID="ContactMaintenanceSelfService" STEPWorkflowStateID="ProcurementEnrichment" UserTypeID="ContactPerson" AttributeGroupID="ProcurementModify"></PrivilegeRule>
            <PrivilegeRule ActionSetID="ProcurementManagerModify" STEPWorkflowID="ContactOnboardingNoSelfService" STEPWorkflowStateID="Initial" UserTypeID="ContactPerson" AttributeGroupID="ProcurementModify"></PrivilegeRule>
            <PrivilegeRule ActionSetID="ProcurementManagerModify" STEPWorkflowID="ContactOnboardingSelfService" STEPWorkflowStateID="InitialEnrichment" UserTypeID="ContactPerson" AttributeGroupID="ProcurementModify"></PrivilegeRule>
            <PrivilegeRule ActionSetID="ProcurementManagerModify" STEPWorkflowID="SupplierMaintenanceNoSelfService" STEPWorkflowStateID="Edit" UserTypeID="Supplier" AttributeGroupID="ProcurementModify"></PrivilegeRule>
            <PrivilegeRule ActionSetID="ProcurementManagerModify" STEPWorkflowID="SupplierMaintenanceSelfService" STEPWorkflowStateID="Initial" UserTypeID="Supplier" AttributeGroupID="ProcurementModify"></PrivilegeRule>
            <PrivilegeRule ActionSetID="ProcurementManagerModify" STEPWorkflowID="SupplierMaintenanceSelfService" STEPWorkflowStateID="ProcurementEnrichment" UserTypeID="Supplier" AttributeGroupID="ProcurementModify"></PrivilegeRule>
            <PrivilegeRule ActionSetID="ProcurementManagerModify" STEPWorkflowID="SupplierOnboardingNoSelfService" STEPWorkflowStateID="Initial" UserTypeID="Supplier" AttributeGroupID="ProcurementModify"></PrivilegeRule>
            <PrivilegeRule ActionSetID="ProcurementManagerModify" STEPWorkflowID="SupplierOnboardingNoSelfService" STEPWorkflowStateID="InitialEnrichment" UserTypeID="Supplier" AttributeGroupID="ProcurementModify"></PrivilegeRule>
            <PrivilegeRule ActionSetID="ProcurementManagerModify" STEPWorkflowID="SupplierOnboardingSelfService" STEPWorkflowStateID="Initial" UserTypeID="Supplier" AttributeGroupID="ProcurementModify"></PrivilegeRule>
            <PrivilegeRule ActionSetID="ProcurementManagerModify" STEPWorkflowID="SupplierOnboardingSelfService" STEPWorkflowStateID="ProcurementEnrichment" UserTypeID="Supplier" AttributeGroupID="ProcurementModify"></PrivilegeRule>
            <PrivilegeRule ActionSetID="ProcurementManagerModify" ClassificationID="SupplierClassificationsRoot" UserTypeID="SupplierAssetsClassification"></PrivilegeRule>
            <PrivilegeRule ActionSetID="ProcurementManagerModify" ClassificationID="SupplierClassificationsRoot" UserTypeID="SupplierClassification"></PrivilegeRule>
            <PrivilegeRule ActionSetID="ProcurementManagerModify" ClassificationID="SupplierClassificationsRoot" UserTypeID="SupplierClassificationsRoot"></PrivilegeRule>
            <PrivilegeRule ActionSetID="ProcurementManagerModify" ClassificationID="SupplierClassificationsRoot" UserTypeID="SupplierEntitiesClassification"></PrivilegeRule>
            <PrivilegeRule ActionSetID="ProcurementManagerModify" ClassificationID="SupplierClassificationsRoot" UserTypeID="SupplierProductsClassification"></PrivilegeRule>
            <PrivilegeRule ActionSetID="ProcurementManagerModify" CollectionGroupID="CollectionGroup root"></PrivilegeRule>
            <PrivilegeRule ActionSetID="ProcurementManagerModify" EntityID="100305" UserTypeID="Aggregate"></PrivilegeRule>
            <PrivilegeRule ActionSetID="ProcurementManagerModify" EntityID="100305" UserTypeID="Region"></PrivilegeRule>
            <PrivilegeRule ActionSetID="ProcurementManagerModify" STEPWorkflowID="ContactOnboardingSelfService" STEPWorkflowStateID="Initial" UserTypeID="ContactPerson"></PrivilegeRule>
            <PrivilegeRule ActionSetID="ProcurementManagerModify" STEPWorkflowID="ContactOnboardingSelfService" STEPWorkflowStateID="ProcurementEnrichment" UserTypeID="ContactPerson"></PrivilegeRule>
            <PrivilegeRule ActionSetID="ProcurementManagerModify" STEPWorkflowID="SupplierOnboardingSelfService" STEPWorkflowStateID="InitialEnrichment" UserTypeID="Supplier"></PrivilegeRule>
            <PrivilegeRule ActionSetID="ProcurementManagerView" ClassificationID="SupplierClassificationsRoot" UserTypeID="SupplierAssetsClassification"></PrivilegeRule>
            <PrivilegeRule ActionSetID="ProcurementManagerView" ClassificationID="SupplierClassificationsRoot" UserTypeID="SupplierClassification"></PrivilegeRule>
            <PrivilegeRule ActionSetID="ProcurementManagerView" ClassificationID="SupplierClassificationsRoot" UserTypeID="SupplierClassificationsRoot"></PrivilegeRule>
            <PrivilegeRule ActionSetID="ProcurementManagerView" ClassificationID="SupplierClassificationsRoot" UserTypeID="SupplierEntitiesClassification"></PrivilegeRule>
            <PrivilegeRule ActionSetID="ProcurementManagerView" ClassificationID="SupplierClassificationsRoot" UserTypeID="SupplierProductsClassification"></PrivilegeRule>
            <PrivilegeRule ActionSetID="ProcurementManagerView" CollectionGroupID="CollectionGroup root"></PrivilegeRule>
            <PrivilegeRule ActionSetID="ProcurementManagerView" EntityID="100305"></PrivilegeRule>
            <PrivilegeRule ActionSetID="ProcurementManagerView" EntityID="100305" UserTypeID="Aggregate"></PrivilegeRule>
            <PrivilegeRule ActionSetID="ProcurementManagerView" EntityID="100305" UserTypeID="ContactPerson"></PrivilegeRule>
            <PrivilegeRule ActionSetID="ProcurementManagerView" EntityID="100305" UserTypeID="ProcurementHierarchyRoot"></PrivilegeRule>
            <PrivilegeRule ActionSetID="ProcurementManagerView" EntityID="100305" UserTypeID="ProcurementManager"></PrivilegeRule>
            <PrivilegeRule ActionSetID="ProcurementManagerView" EntityID="100305" UserTypeID="Region"></PrivilegeRule>
            <PrivilegeRule ActionSetID="ProcurementManagerView" EntityID="100305" UserTypeID="Supplier"></PrivilegeRule>
            <PrivilegeRule ActionSetID="ProcurementManagerView" EntityID="100305" UserTypeID="Territory"></PrivilegeRule>
            <PrivilegeRule ActionSetID="ProcurementSetupActions"></PrivilegeRule>
        </UserGroup>
    </UserGroupList>
</STEP-ProductInformation>